litlogger/__init__.py
litlogger/_module.py
litlogger/_preinit.py
litlogger/artifacts.py
litlogger/background.py
litlogger/colors.py
litlogger/diagnostics.py
litlogger/experiment.py
litlogger/file_writer.py
litlogger/generator.py
litlogger/init.py
litlogger/logger.py
litlogger/printer.py
litlogger/types.py
litlogger/api/__init__.py
litlogger/api/artifacts_api.py
litlogger/api/auth_api.py
litlogger/api/client.py
litlogger/api/metrics_api.py
litlogger/api/utils.py
litlogger/capture/__init__.py
litlogger/capture/posix.py
litlogger/capture/windows.py
litlogger-0.1.6.dist-info/LICENSE
litlogger-0.1.6.dist-info/METADATA
litlogger-0.1.6.dist-info/WHEEL
litlogger-0.1.6.dist-info/top_level.txt
litlogger-0.1.6.dist-info/RECORD
