Metadata-Version: 2.1
Name: litlogger
Version: 0.1.6
Summary: The Lightning Logger of the Lightning.AI Platform
Author-email: Lightning-AI <thomas@lightning.ai>
License: Apache License
Keywords: deep learning,machine learning,pytorch,AI
Classifier: Programming Language :: Python :: 3
Requires-Python: >=3.10
License-File: LICENSE
Requires-Dist: lightning-sdk>=2025.12.17
Requires-Dist: litmodels>=0.1.8
Requires-Dist: protobuf
Requires-Dist: psutil
Requires-Dist: rich
